azure/communication/__init__.py
azure_communication_nspkg-0.0.0b1.dist-info/METADATA
azure_communication_nspkg-0.0.0b1.dist-info/WHEEL
azure_communication_nspkg-0.0.0b1.dist-info/top_level.txt
azure_communication_nspkg-0.0.0b1.dist-info/RECORD
